django_power_admin/__init__.py
django_power_admin/admin.py
django_power_admin/apps.py
django_power_admin/exceptions.py
django_power_admin/fields.py
django_power_admin/filters.py
django_power_admin/models.py
django_power_admin/tests.py
django_power_admin/utils.py
django_power_admin/views.py
django_power_admin/widgets.py
django_power_admin/locale/zh_Hans/LC_MESSAGES/django.mo
django_power_admin/locale/zh_Hans/LC_MESSAGES/django.po
django_power_admin/migrations/__init__.py
django_power_admin/static/django_power_admin/admin/SimpleImportAdmin/css/SimpleImportAdmin.css
django_power_admin/static/django_power_admin/admin/SimpleImportAdmin/js/SimpleImportAdmin.js
django_power_admin/static/django_power_admin/admin/css/AdminExtends.css
django_power_admin/static/django_power_admin/admin/css/AdminFix.css
django_power_admin/static/django_power_admin/admin/css/ChangelistHighlightRow.css
django_power_admin/static/django_power_admin/admin/css/ChangelistObjectToolbar.css
django_power_admin/static/django_power_admin/admin/css/ChangelistToolbar.css
django_power_admin/static/django_power_admin/admin/css/Sortable.css
django_power_admin/static/django_power_admin/admin/js/ChangelistHighlightRow.js
django_power_admin/static/django_power_admin/admin/js/ChangelistToolbar.js
django_power_admin/static/django_power_admin/assets/css/WorkflowProgressBar.css
django_power_admin/static/django_power_admin/assets/js/WorkflowProgressBar.js
django_power_admin/static/django_power_admin/assets/js/parseParam.js
django_power_admin/static/django_power_admin/filters/DateRangeFilter/css/DateRangeFilter.css
django_power_admin/static/django_power_admin/filters/DateRangeFilter/js/DateRangeFilter.js
django_power_admin/static/django_power_admin/filters/TextInputFieldFilter/css/TextInputFieldFilter.css
django_power_admin/static/django_power_admin/filters/TextInputFieldFilter/js/TextInputFieldFilter.js
django_power_admin/static/django_power_admin/widgets/ConfigTable/css/ConfigTable.css
django_power_admin-0.1.37.dist-info/LICENSE
django_power_admin-0.1.37.dist-info/METADATA
django_power_admin-0.1.37.dist-info/WHEEL
django_power_admin-0.1.37.dist-info/top_level.txt
django_power_admin-0.1.37.dist-info/RECORD
