Metadata-Version: 2.1
Name: django-power-admin
Version: 0.1.37
Summary: Django提供了快捷的生成后台管理站点的能力。本应用旨在增强Django Admin的能力，提供丰富的Admin、Widget、ListFilter、Form等等界面扩展类，同时也为常用的数据管理模型提供完整的管理功能。
Author: He LianJia
Author-email: helianjia@zencore.cn
Maintainer: He LianJia
Maintainer-email: helianjia@zencore.cn
License: MIT
Keywords: django,django admin,django power admin,django admin extensions
Classifier: Development Status :: 5 - Production/Stable
Classifier: Intended Audience :: Developers
Classifier: Topic :: Software Development :: Libraries :: Python Modules
Classifier: License :: OSI Approved :: MIT License
Classifier: Programming Language :: Python :: 3
Classifier: Programming Language :: Python :: 3 :: Only
License-File: LICENSE
Requires-Dist: django
Requires-Dist: django-simple-tags
Requires-Dist: django-middleware-global-request
Requires-Dist: django-static-fontawesome
Requires-Dist: django-static-jquery-ui
Requires-Dist: django-app-requires
Requires-Dist: django-mptt
Requires-Dist: openpyxl
Requires-Dist: xlsxhelper
Requires-Dist: zenutils
Requires-Dist: pwgen
